pytun_pmd3/__init__.py
pytun_pmd3/_version.py
pytun_pmd3/darwin.py
pytun_pmd3/exceptions.py
pytun_pmd3/linux.py
pytun_pmd3/wintun.py
pytun_pmd3/wintun/LICENSE.txt
pytun_pmd3/wintun/README.md
pytun_pmd3/wintun/bin/amd64/wintun.dll
pytun_pmd3/wintun/bin/arm/wintun.dll
pytun_pmd3/wintun/bin/arm64/wintun.dll
pytun_pmd3/wintun/bin/x86/wintun.dll
pytun_pmd3/wintun/include/wintun.h
pytun_pmd3-3.0.1.dist-info/licenses/LICENSE
pytun_pmd3-3.0.1.dist-info/METADATA
pytun_pmd3-3.0.1.dist-info/WHEEL
pytun_pmd3-3.0.1.dist-info/top_level.txt
pytun_pmd3-3.0.1.dist-info/RECORD
