Metadata-Version: 2.4
Name: pytun-pmd3
Version: 3.0.1
Summary: python-pytun fork with darwin and windows support (IPv6-ONLY)
Author-email: doronz88 <doron88@gmail.com>
Maintainer-email: doronz88 <doron88@gmail.com>
License: Copyright (c) 2011, montag451.
Project-URL: Homepage, https://github.com/doronz88/pytun-pmd3
Project-URL: Bug Reports, https://github.com/doronz88/pytun-pmd3/issues
Keywords: tun,tuntap,darwin,pymobiledevice3,macos,windows
Classifier: Development Status :: 5 - Production/Stable
Classifier: License :: OSI Approved :: GNU General Public License v3 or later (GPLv3+)
Classifier: Programming Language :: Python :: 3
Classifier: Programming Language :: Python :: 3.9
Classifier: Programming Language :: Python :: 3.10
Classifier: Programming Language :: Python :: 3.11
Classifier: Programming Language :: Python :: 3.12
Classifier: Programming Language :: Python :: 3.13
Classifier: Programming Language :: Python :: 3 :: Only
Requires-Python: >=3.8
License-File: LICENSE
Provides-Extra: test
Requires-Dist: pytest; extra == "test"
Dynamic: license-file
